metacountregressor/__init__.py
metacountregressor/_device_cust.py
metacountregressor/app_main.py
metacountregressor/data_split_helper.py
metacountregressor/halton.py
metacountregressor/helperprocess.py
metacountregressor/main.py
metacountregressor/main_old.py
metacountregressor/metaheuristics.py
metacountregressor/pareto_file.py
metacountregressor/pareto_logger__plot.py
metacountregressor/setup.py
metacountregressor/single_objective_finder.py
metacountregressor/solution.py
metacountregressor/test_code.py
metacountregressor/test_generated_paper2.py
metacountregressor-1.0.19.dist-info/licenses/LICENSE.txt
metacountregressor-1.0.19.dist-info/METADATA
metacountregressor-1.0.19.dist-info/WHEEL
metacountregressor-1.0.19.dist-info/top_level.txt
metacountregressor-1.0.19.dist-info/RECORD
