Metadata-Version: 2.4
Name: metacountregressor
Version: 1.0.19
Summary: Extensive Testing for Estimation of Data Count Models
Home-page: https://github.com/zahern/CountDataEstimation
Author: Zeke Ahern, Alexander Paz
Author-email: z.ahern@qut.edu.au
License: MIT
Requires-Python: >=3.10
License-File: LICENSE.txt
Requires-Dist: numpy<2.0.0
Requires-Dist: requests<3.0.0,>=2.20.0
Requires-Dist: latextable
Requires-Dist: pandas!=2.1.0,>=1.4
Requires-Dist: scikit-learn>=1.3.1
Requires-Dist: statsmodels
Requires-Dist: psutil
Requires-Dist: matplotlib>=3.0.0
Requires-Dist: pybind11<3.0.0,>=2.12
Dynamic: author
Dynamic: author-email
Dynamic: description
Dynamic: description-content-type
Dynamic: home-page
Dynamic: license
Dynamic: license-file
Dynamic: requires-dist
Dynamic: requires-python
Dynamic: summary
